{
  "integration": [
    {
      "question": "What is the integral of sin(ax)*cos(bx)?",
      "options": [
        "(sin((a + b)x) - sin((a - b)x))/(2(a + b)) + C",
        "(cos((a + b)x) + cos((a - b)x))/(2(a - b)) + C",
        "x^2/2",
        "cos(x)"
      ],
      "answer": "(sin((a + b)x) - sin((a - b)x))/(2(a + b)) + C"
    },
    {
      "question": "What is the integral of sec(x)*tan(x)?",
      "options": ["sec(x)", "csc(x)", "cot(x)", "x"],
      "answer": "sec(x) + C"
    },
    {
      "question": "What is the integral of csc(x)*cot(x)?",
      "options": ["-csc(x)", "cot(x)", "ln|csc(x)| + C", "x"],
      "answer": "-ln|sin(x)| + C"
    },
    {
      "question": "What is the integral of sec(x)*cot(x)?",
      "options": ["-ln|cos(x)| + C", "cot(x)", "sec(x)", "x"],
      "answer": "-ln|cos(x)| + C"
    },
    {
      "question": "What is the integral of sqrt(1 - x^2)?",
      "options": [
        "(1/2)(x*sqrt(1 - x^2) + arcsin(x)) + C",
        "tan(x)",
        "1/x",
        "cos(x)"
      ],
      "answer": "(1/2)(x*sqrt(1 - x^2) + arcsin(x)) + C"
    },
    {
      "question": "What is the integral of sqrt(1 + x^2)?",
      "options": [
        "(1/2)(x*sqrt(1 + x^2) + x + ln|x + sqrt(1 + x^2)|) + C",
        "tan(x)",
        "1/x",
        "sin(x)"
      ],
      "answer": "(1/2)(x*sqrt(1 + x^2) + x + ln|x + sqrt(1 + x^2)|) + C"
    },
    {
      "question": "What is the integral of sqrt(x^2 - 1)?",
      "options": [
        "(1/2)(x*sqrt(x^2 - 1) - x + ln|x + sqrt(x^2 - 1)|) + C",
        "tan(x)",
        "1/x",
        "cos(x)"
      ],
      "answer": "(1/2)(x*sqrt(x^2 - 1) - x + ln|x + sqrt(x^2 - 1)|) + C"
    },
    {
      "question": "What is the integral of 1/sqrt(x^2 - 1)?",
      "options": ["sinh(x) + C", "cosh(x) + C", "tan(x)", "cos(x)"],
      "answer": "ln|x + sqrt(x^2 - 1)| + C"
    },
    {
      "question": "What is the integral of 1/sqrt(1 - x^2)?",
      "options": ["sinh(x) + C", "cosh(x) + C", "tan(x)", "cos(x)"],
      "answer": "arcsin(x) + C"
    },
    {
      "question": "What is the integral of sin(ax)*sin(bx)?",
      "options": [
        "(cos((a - b)x) - cos((a + b)x))/(2(a - b)) + C",
        "cos(ax)*cos(bx) + C",
        "x^2/2",
        "cos(x)"
      ],
      "answer": "(cos((a - b)x) - cos((a + b)x))/(2(a - b)) + C"
    },
    {
      "question": "What is the integral of cos(ax)*cos(bx)?",
      "options": [
        "(sin((a + b)x) + sin((a - b)x))/(2(a + b)) + C",
        "sin(ax)*sin(bx) + C",
        "x^2/2",
        "sin(x)"
      ],
      "answer": "(sin((a + b)x) + sin((a - b)x))/(2(a + b)) + C"
    },
    {
      "question": "What is the integral of sin(ax)*cos(bx)?",
      "options": [
        "(sin((a + b)x) - sin((a - b)x))/(2(a + b)) + C",
        "(cos((a + b)x) + cos((a - b)x))/(2(a - b)) + C",
        "x^2/2",
        "cos(x)"
      ],
      "answer": "(sin((a + b)x) - sin((a - b)x))/(2(a + b)) + C"
    },
    {
      "question": "What is the integral of sec(x)*tan(x)?",
      "options": ["sec(x)", "csc(x)", "cot(x)", "x"],
      "answer": "sec(x) + C"
    },
    {
      "question": "What is the integral of csc(x)*cot(x)?",
      "options": ["-csc(x)", "cot(x)", "ln|csc(x)| + C", "x"],
      "answer": "-ln|sin(x)| + C"
    },
    {
      "question": "What is the integral of sec(x)*cot(x)?",
      "options": ["-ln|cos(x)| + C", "cot(x)", "sec(x)", "x"],
      "answer": "-ln|cos(x)| + C"
    },
    {
      "question": "What is the integral of sqrt(1 - x^2)?",
      "options": [
        "(1/2)(x*sqrt(1 - x^2) + arcsin(x)) + C",
        "tan(x)",
        "1/x",
        "cos(x)"
      ],
      "answer": "(1/2)(x*sqrt(1 - x^2) + arcsin(x)) + C"
    },
    {
      "question": "What is the integral of sqrt(1 + x^2)?",
      "options": [
        "(1/2)(x*sqrt(1 + x^2) + x + ln|x + sqrt(1 + x^2)|) + C",
        "tan(x)",
        "1/x",
        "sin(x)"
      ],
      "answer": "(1/2)(x*sqrt(1 + x^2) + x + ln|x + sqrt(1 + x^2)|) + C"
    },
    {
      "question": "What is the integral of sqrt(x^2 - 1)?",
      "options": [
        "(1/2)(x*sqrt(x^2 - 1) - x + ln|x + sqrt(x^2 - 1)|) + C",
        "tan(x)",
        "1/x",
        "cos(x)"
      ],
      "answer": "(1/2)(x*sqrt(x^2 - 1) - x + ln|x + sqrt(x^2 - 1)|) + C"
    },
    {
      "question": "What is the integral of 1/sqrt(x^2 - 1)?",
      "options": ["sinh(x) + C", "cosh(x) + C", "tan(x)", "cos(x)"],
      "answer": "ln|x + sqrt(x^2 - 1)| + C"
    },
    {
      "question": "What is the integral of 1/sqrt(1 - x^2)?",
      "options": ["sinh(x) + C", "cosh(x) + C", "tan(x)", "cos(x)"],
      "answer": "arcsin(x) + C"
    },
    {
      "question": "What is the integral of sin(ax)*sin(bx)?",
      "options": [
        "(cos((a - b)x) - cos((a + b)x))/(2(a - b)) + C",
        "cos(ax)*cos(bx) + C",
        "x^2/2",
        "cos(x)"
      ],
      "answer": "(cos((a - b)x) - cos((a + b)x))/(2(a - b)) + C"
    },
    {
      "question": "What is the integral of cos(ax)*cos(bx)?",
      "options": [
        "(sin((a + b)x) + sin((a - b)x))/(2(a + b)) + C",
        "sin(ax)*sin(bx) + C",
        "x^2/2",
        "sin(x)"
      ],
      "answer": "(sin((a + b)x) + sin((a - b)x))/(2(a + b)) + C"
    },
    {
      "question": "What is the integral of sin(ax)*cos(bx)?",
      "options": [
        "(sin((a + b)x) - sin((a - b)x))/(2(a + b)) + C",
        "(cos((a + b)x) + cos((a - b)x))/(2(a - b)) + C",
        "x^2/2",
        "cos(x)"
      ],
      "answer": "(sin((a + b)x) - sin((a - b)x))/(2(a + b)) + C"
    },
    {
      "question": "What is the integral of sec(x)*tan(x)?",
      "options": ["sec(x)", "csc(x)", "cot(x)", "x"],
      "answer": "sec(x) + C"
    },
    {
      "question": "What is the integral of csc(x)*cot(x)?",
      "options": ["-csc(x)", "cot(x)", "ln|csc(x)| + C", "x"],
      "answer": "-ln|sin(x)| + C"
    },
    {
      "question": "What is the integral of sec(x)*cot(x)?",
      "options": ["-ln|cos(x)| + C", "cot(x)", "sec(x)", "x"],
      "answer": "-ln|cos(x)| + C"
    },
    {
      "question": "What is the integral of sqrt(1 - x^2)?",
      "options": [
        "(1/2)(x*sqrt(1 - x^2) + arcsin(x)) + C",
        "tan(x)",
        "1/x",
        "cos(x)"
      ],
      "answer": "(1/2)(x*sqrt(1 - x^2) + arcsin(x)) + C"
    },
    {
      "question": "What is the integral of sqrt(1 + x^2)?",
      "options": [
        "(1/2)(x*sqrt(1 + x^2) + x + ln|x + sqrt(1 + x^2)|) + C",
        "tan(x)",
        "1/x",
        "sin(x)"
      ],
      "answer": "(1/2)(x*sqrt(1 + x^2) + x + ln|x + sqrt(1 + x^2)|) + C"
    },
    {
      "question": "What is the integral of sqrt(x^2 - 1)?",
      "options": [
        "(1/2)(x*sqrt(x^2 - 1) - x + ln|x + sqrt(x^2 - 1)|) + C",
        "tan(x)",
        "1/x",
        "cos(x)"
      ],
      "answer": "(1/2)(x*sqrt(x^2 - 1) - x + ln|x + sqrt(x^2 - 1)|) + C"
    },
    {
      "question": "What is the integral of 1/sqrt(x^2 - 1)?",
      "options": ["sinh(x) + C", "cosh(x) + C", "tan(x)", "cos(x)"],
      "answer": "ln|x + sqrt(x^2 - 1)| + C"
    },
    {
      "question": "What is the integral of 1/sqrt(1 - x^2)?",
      "options": ["sinh(x) + C", "cosh(x) + C", "tan(x)", "cos(x)"],
      "answer": "arcsin(x) + C"
    }
  ],
  "differentiation": [
    {
      "question": "What is the derivative of x^n?",
      "options": ["nx^(n-1)", "(1/n+1)x^(n+1)", "x^(n+1)", "x^n + C"],
      "answer": "nx^(n-1)"
    },
    {
      "question": "What is the derivative of e^x?",
      "options": ["e^x + C", "ln(x) + C", "x^2/2", "sin(x)"],
      "answer": "e^x"
    },
    {
      "question": "What is the derivative of sin(x)?",
      "options": ["cos(x)", "-cos(x)", "tan(x)", "csc(x)"],
      "answer": "cos(x)"
    },
    {
      "question": "What is the derivative of cos(x)?",
      "options": ["cos(x)", "sin(x)", "tan(x)", "-cos(x) + C"],
      "answer": "-sin(x)"
    },
    {
      "question": "What is the derivative of tan(x)?",
      "options": ["sec^2(x)", "csc^2(x)", "sin(x)", "cos(x)"],
      "answer": "sec^2(x)"
    },
    {
      "question": "What is the derivative of sec(x)?",
      "options": ["sec(x)tan(x)", "csc(x)cot(x)", "cos(x)", "sin(x)"],
      "answer": "sec(x)tan(x)"
    },
    {
      "question": "What is the derivative of csc(x)?",
      "options": ["-csc(x)cot(x)", "sec(x)tan(x)", "cos(x)", "sin(x)"],
      "answer": "-csc(x)cot(x)"
    },
    {
      "question": "What is the derivative of cot(x)?",
      "options": ["-csc^2(x)", "sec^2(x)", "cos(x)", "sin(x)"],
      "answer": "-csc^2(x)"
    },
    {
      "question": "What is the derivative of ln(x)?",
      "options": ["1/x", "x", "e^x", "cos(x)"],
      "answer": "1/x"
    },
    {
      "question": "What is the derivative of sqrt(x)?",
      "options": ["1/(2sqrt(x))", "2sqrt(x)", "1/x", "x^2/2"],
      "answer": "1/(2sqrt(x))"
    },
    {
      "question": "What is the derivative of 1/x?",
      "options": ["-1/x^2", "ln(x)", "x^2/2", "1/x + C"],
      "answer": "-1/x^2"
    },
    {
      "question": "What is the derivative of arcsin(x)?",
      "options": ["1/sqrt(1-x^2)", "-1/sqrt(1-x^2)", "cos(x)", "sin(x)"],
      "answer": "1/sqrt(1-x^2)"
    },
    {
      "question": "What is the derivative of arccos(x)?",
      "options": ["-1/sqrt(1-x^2)", "1/sqrt(1-x^2)", "cos(x)", "sin(x)"],
      "answer": "-1/sqrt(1-x^2)"
    },
    {
      "question": "What is the derivative of arctan(x)?",
      "options": ["1/(1+x^2)", "-1/(1+x^2)", "cos(x)", "sin(x)"],
      "answer": "1/(1+x^2)"
    },
    {
      "question": "What is the derivative of sinh(x)?",
      "options": ["cosh(x)", "sinh(x)", "cosh(x) + C", "sinh(x) + C"],
      "answer": "cosh(x)"
    },
    {
      "question": "What is the derivative of cosh(x)?",
      "options": ["sinh(x)", "cosh(x)", "sinh(x) + C", "cosh(x) + C"],
      "answer": "sinh(x)"
    },
    {
      "question": "What is the derivative of tanh(x)?",
      "options": ["sech^2(x)", "sech(x)", "cosh(x)", "sinh(x)"],
      "answer": "sech^2(x)"
    },
    {
      "question": "What is the derivative of sech(x)?",
      "options": ["-sech(x)tanh(x)", "sech(x)tanh(x)", "cosh(x)", "sinh(x)"],
      "answer": "-sech(x)tanh(x)"
    },
    {
      "question": "What is the derivative of csch(x)?",
      "options": ["-csch(x)coth(x)", "csch(x)coth(x)", "cosh(x)", "sinh(x)"],
      "answer": "-csch(x)coth(x)"
    },
    {
      "question": "What is the derivative of coth(x)?",
      "options": ["-csch^2(x)", "csch^2(x)", "cosh(x)", "sinh(x)"],
      "answer": "-csch^2(x)"
    },
    {
      "question": "What is the derivative of log_a(x)?",
      "options": ["1/(xln(a))", "ln(x)", "x^(1/a)", "1/x"],
      "answer": "1/(xln(a))"
    },
    {
      "question": "What is the derivative of a^x?",
      "options": ["a^xln(a)", "ln(x)", "x^a", "1/x"],
      "answer": "a^xln(a)"
    },
    {
      "question": "What is the derivative of log_b(x)?",
      "options": ["1/(xln(b))", "ln(x)", "x^(1/b)", "1/x"],
      "answer": "1/(xln(b))"
    },
    {
      "question": "What is the derivative of log_b(a^x)?",
      "options": ["a^xln(b)", "ln(x)", "x^a", "1/x"],
      "answer": "a^xln(b)"
    },
    {
      "question": "What is the derivative of log_a(b^x)?",
      "options": ["xln(b)/ln(a)", "ln(x)", "x^a", "1/x"],
      "answer": "xln(b)/ln(a)"
    },
    {
      "question": "What is the derivative of log_a(x^b)?",
      "options": ["bln(x)/ln(a)", "ln(x)", "x^a", "1/x"],
      "answer": "bln(x)/ln(a)"
    },
    {
      "question": "What is the derivative of a^(bx)?",
      "options": ["ab^xln(a)", "ln(x)", "x^a", "1/x"],
      "answer": "ab^xln(a)"
    },
    {
      "question": "What is the derivative of (1+x)^n?",
      "options": [
        "n(1+x)^(n-1)",
        "(1/n+1)(1+x)^(n+1)",
        "(1+x)^(n+1)",
        "(1+x)^n + C"
      ],
      "answer": "n(1+x)^(n-1)"
    },
    {
      "question": "What is the derivative of log(x+c)?",
      "options": ["1/(x+c)", "ln(x)", "x^c", "1/x"],
      "answer": "1/(x+c)"
    }
  ]
}
